setup.py
src/toolbox/__init__.py
src/toolbox/module_a.py
tinsopy-0.0.2.dist-info/METADATA
tinsopy-0.0.2.dist-info/WHEEL
tinsopy-0.0.2.dist-info/licenses/LICENSE
tinsopy-0.0.2.dist-info/RECORD
